{
  "global": {
    "fontFamilies": {
      "golos-text": {
        "value": "Golos Text",
        "type": "fontFamilies",
        "filePath": "tokens/tokens.json",
        "isSource": true,
        "original": {
          "value": "Golos Text",
          "type": "fontFamilies"
        },
        "name": "GlobalFontFamiliesGolosText",
        "attributes": {
          "category": "global",
          "type": "fontFamilies",
          "item": "golos-text"
        },
        "path": [
          "global",
          "fontFamilies",
          "golos-text"
        ]
      }
    },
    "fontWeights": {
      "golos-text-0": {
        "value": "Medium",
        "type": "fontWeights",
        "filePath": "tokens/tokens.json",
        "isSource": true,
        "original": {
          "value": "Medium",
          "type": "fontWeights"
        },
        "name": "GlobalFontWeightsGolosText0",
        "attributes": {
          "category": "global",
          "type": "fontWeights",
          "item": "golos-text-0"
        },
        "path": [
          "global",
          "fontWeights",
          "golos-text-0"
        ]
      }
    },
    "fontSize": {
      "0": {
        "value": "46px",
        "type": "fontSizes",
        "filePath": "tokens/tokens.json",
        "isSource": true,
        "original": {
          "value": "46px",
          "type": "fontSizes"
        },
        "name": "GlobalFontSize0",
        "attributes": {
          "category": "global",
          "type": "fontSize",
          "item": "0"
        },
        "path": [
          "global",
          "fontSize",
          "0"
        ]
      }
    },
    "lineHeights": {
      "0": {
        "value": "120%",
        "type": "lineHeights",
        "filePath": "tokens/tokens.json",
        "isSource": true,
        "original": {
          "value": "120%",
          "type": "lineHeights"
        },
        "name": "GlobalLineHeights0",
        "attributes": {
          "category": "global",
          "type": "lineHeights",
          "item": "0"
        },
        "path": [
          "global",
          "lineHeights",
          "0"
        ]
      }
    },
    "letterSpacing": {
      "0": {
        "value": "0",
        "type": "letterSpacing",
        "filePath": "tokens/tokens.json",
        "isSource": true,
        "original": {
          "value": "0",
          "type": "letterSpacing"
        },
        "name": "GlobalLetterSpacing0",
        "attributes": {
          "category": "global",
          "type": "letterSpacing",
          "item": "0"
        },
        "path": [
          "global",
          "letterSpacing",
          "0"
        ]
      }
    },
    "paragraphSpacing": {
      "0": {
        "value": "0",
        "type": "paragraphSpacing",
        "filePath": "tokens/tokens.json",
        "isSource": true,
        "original": {
          "value": "0",
          "type": "paragraphSpacing"
        },
        "name": "GlobalParagraphSpacing0",
        "attributes": {
          "category": "global",
          "type": "paragraphSpacing",
          "item": "0"
        },
        "path": [
          "global",
          "paragraphSpacing",
          "0"
        ]
      }
    },
    "paragraphIndent": {
      "0": {
        "value": "0",
        "type": "paragraphIndent",
        "filePath": "tokens/tokens.json",
        "isSource": true,
        "original": {
          "value": "0",
          "type": "paragraphIndent"
        },
        "name": "GlobalParagraphIndent0",
        "attributes": {
          "category": "global",
          "type": "paragraphIndent",
          "item": "0"
        },
        "path": [
          "global",
          "paragraphIndent",
          "0"
        ]
      }
    },
    "Medium": {
      "Type@46": {
        "value": {
          "fontFamily": "Golos Text",
          "fontWeight": "Medium",
          "lineHeight": "120%",
          "fontSize": "46px",
          "letterSpacing": "0",
          "paragraphSpacing": "0",
          "paragraphIndent": "0"
        },
        "type": "typography",
        "filePath": "tokens/tokens.json",
        "isSource": true,
        "original": {
          "value": {
            "fontFamily": "Golos Text",
            "fontWeight": "Medium",
            "lineHeight": "120%",
            "fontSize": "46px",
            "letterSpacing": "0",
            "paragraphSpacing": "0",
            "paragraphIndent": "0"
          },
          "type": "typography"
        },
        "name": "GlobalMediumType46",
        "attributes": {
          "category": "global",
          "type": "Medium",
          "item": "Type@46"
        },
        "path": [
          "global",
          "Medium",
          "Type@46"
        ]
      }
    }
  }
}
